collective.collabora-1.1.0-py3.10-nspkg.pth
collective/collabora/__init__.py
collective/collabora/adapters.py
collective/collabora/configure.zcml
collective/collabora/interfaces.py
collective/collabora/setuphandlers.py
collective/collabora/testing.py
collective/collabora/utils.py
collective/collabora/browser/__init__.py
collective/collabora/browser/configure.zcml
collective/collabora/browser/edit.py
collective/collabora/browser/wopi.py
collective/collabora/browser/static/edit.css
collective/collabora/browser/static/edit.js
collective/collabora/browser/templates/edit.pt
collective/collabora/locales/README.rst
collective/collabora/locales/__init__.py
collective/collabora/locales/collective.collabora.pot
collective/collabora/locales/update.py
collective/collabora/locales/update.sh
collective/collabora/locales/de/LC_MESSAGES/collective.collabora.po
collective/collabora/locales/en/LC_MESSAGES/collective.collabora.po
collective/collabora/locales/es/LC_MESSAGES/collective.collabora.po
collective/collabora/locales/fr/LC_MESSAGES/collective.collabora.po
collective/collabora/locales/nl/LC_MESSAGES/collective.collabora.po
collective/collabora/profiles/default/browserlayer.xml
collective/collabora/profiles/default/metadata.xml
collective/collabora/profiles/default/registry.xml
collective/collabora/profiles/default/types.xml
collective/collabora/profiles/default/types/File.xml
collective/collabora/profiles/uninstall/browserlayer.xml
collective/collabora/testdata/server_discovery_xml
collective/collabora/testdata/testfile.docx
collective/collabora/tests/__init__.py
collective/collabora/tests/test_adapters.py
collective/collabora/tests/test_edit.py
collective/collabora/tests/test_setup.py
collective/collabora/tests/test_utils.py
collective/collabora/tests/test_wopi.py
collective.collabora-1.1.0.dist-info/LICENSE.GPL
collective.collabora-1.1.0.dist-info/LICENSE.rst
collective.collabora-1.1.0.dist-info/METADATA
collective.collabora-1.1.0.dist-info/WHEEL
collective.collabora-1.1.0.dist-info/entry_points.txt
collective.collabora-1.1.0.dist-info/namespace_packages.txt
collective.collabora-1.1.0.dist-info/top_level.txt
collective.collabora-1.1.0.dist-info/RECORD
