Metadata-Version: 2.1
Name: collective.collabora
Version: 1.1.0
Summary: Collabora Online integration for Plone
Home-page: https://github.com/collective/collective.collabora
Author: Guido A.J. Stevens
Author-email: guido.stevens@cosent.net
License: GPL version 2
Project-URL: PyPI, https://pypi.org/project/collective.collabora/
Project-URL: Source, https://github.com/collective/collective.collabora
Project-URL: Tracker, https://github.com/collective/collective.collabora/issues
Project-URL: Documentation, https://collectivecollabora.readthedocs.io/en/latest/
Keywords: Python Plone CMS
Classifier: Development Status :: 4 - Beta
Classifier: Environment :: Web Environment
Classifier: Framework :: Plone
Classifier: Framework :: Plone :: Addon
Classifier: Framework :: Plone :: 4.3
Classifier: Framework :: Plone :: 5.2
Classifier: Framework :: Plone :: 6.0
Classifier: Framework :: Plone :: 6.1
Classifier: Programming Language :: Python
Classifier: Programming Language :: Python :: 2.7
Classifier: Programming Language :: Python :: 3.8
Classifier: Programming Language :: Python :: 3.9
Classifier: Programming Language :: Python :: 3.10
Classifier: Programming Language :: Python :: 3.11
Classifier: Programming Language :: Python :: 3.12
Classifier: Programming Language :: Python :: 3.13
Classifier: Operating System :: OS Independent
Classifier: License :: OSI Approved :: GNU General Public License v2 (GPLv2)
Requires-Python: >=2.7,!=3.0.*,!=3.1.*,!=3.2.*,!=3.3.*,!=3.4.*,!=3.5.*,!=3.6.*,!=3.7.*
License-File: LICENSE.GPL
License-File: LICENSE.rst
Requires-Dist: setuptools
Requires-Dist: future
Requires-Dist: plone.api
Requires-Dist: plone.app.contenttypes
Requires-Dist: plone.protect
Requires-Dist: plone.restapi
Requires-Dist: python-dateutil
Provides-Extra: test
Requires-Dist: mock; extra == "test"
Requires-Dist: plone.app.testing; extra == "test"
Requires-Dist: plone.testing; extra == "test"
